{
    "book": "001",
    "height": 750,
    "original": "http://124.33.215.236/research/atoinga/001/page92/x1.jpg",
    "page": 92,
    "text": "●大豆囤積（開原にて）　特産の出盛りに鐵道沿線の各驛に集積する大豆の總量は實に大いしたものだ。此季節に糧棧の庭先にはアンペラ圍ひの貯藏庫が急造される、之れを囤と稱して簡易な造作であるが穀物類の蓄積には理想的のものである。一山約五百六十石（百二十噸）の容量を有し高一丈六尺、直徑十尺位、屋根の構造も勿論風雨に堪江られるものだ。貯藏大豆を取出す時には側腹に穴を明けて自然に流出させる點など却々勞力手數の簡略法として妙を得て居る。　（印畫の複製を嚴禁す）／／●大豆囤積（開原にて）　特産の出盛りに鉄道沿線の各駅に集積する大豆の総量は実に大いしたものだ。此季節に糧桟の庭先にはアンペラ囲ひの貯蔵庫が急造される、之れを囤と称して簡易な造作であるが穀物類の蓄積には理想的のものである。一山約五百六十石（百二十噸）の容量を有し高一丈六尺、直径十尺位、屋根の構造も勿論風雨に堪江られるものだ。貯蔵大豆を取出す時には側腹に穴を明けて自然に流出させる点など却々労力手数の簡略法として妙を得て居る。　（印画の複製を厳禁す）",
    "thumbnail": "http://124.33.215.236/research/atoinga/001/page92/thumbnail.jpg",
    "width": 985
}