{
    "book": "001",
    "height": 770,
    "original": "http://124.33.215.236/research/atoinga/003/page81/x1.jpg",
    "page": 81,
    "text": "●土窟の我が家へ（山西省）　短い秋の陽は西に廻つて夕暮に近き溝道の片側は冷い䕃で黑い。　客を送つてのカマボコ馬車は一瓶の土酒を町から購ひ求めて土窟の我が家へと急ぐ。奶々はやがて燈心の豆ランプを灯して夫の歸りを待つことであらう。　（印畫の複製を嚴禁す）／／●土窟の我が家へ（山西省）　短い秋の陽は西に廻つて夕暮に近き溝道の片側は冷い蔭で黒い。　客を送つてのカマボコ馬車は一瓶の土酒を町から購ひ求めて土窟の我が家へと急ぐ。奶々はやがて灯心の豆ランプを灯して夫の帰りを待つことであらう。　（印画の複製を厳禁す）",
    "thumbnail": "http://124.33.215.236/research/atoinga/003/page81/thumbnail.jpg",
    "width": 985
}