{
    "book": "001",
    "height": 775,
    "original": "http://124.33.215.236/research/atoinga/004/page108/x1.jpg",
    "page": 108,
    "text": "●葛田里の勝景（鴨綠江）　江中第一の勝景葛田里は、新乫坡より二十五邦里の下流に在る。嵐峡に似た山せまり水よどむ麗凉の境で緩く流るゝ筏の景色も畫中の一点景である。　筏夫の唄ふいかだ節のメロデイにつれて𧮾の鷲の交響樂を聞くものは鴨江自分にして詩あるを悟るであろう　（印畫の複製を嚴禁す）／／●葛田里の勝景（鴨緑江）江中第一の勝景葛田里は、新乫坡より二十五邦里の下流に在る。嵐峡に似た山せまり水よどむ麗凉の境で緩く流るゝ筏の景色も画中の一点景である。　筏夫の唄ふいかだ節のメロデイにつれて𧮾の鷲の交響楽を聞くものは鴨江自分にして詩あるを悟るであろう　（印画の複製を厳禁す）",
    "thumbnail": "http://124.33.215.236/research/atoinga/004/page108/thumbnail.jpg",
    "width": 985
}