{
    "book": "001",
    "height": 760,
    "original": "http://124.33.215.236/research/atoinga/005/page139/x1.jpg",
    "page": 139,
    "text": "●模範監獄（濟南）　濟南の新式模範監獄は支那としては珍らしい名施設だ。如何にも明るに淸々しい此の建物から受ける印象は、牢獄と云ふ陰慘な暗黑さを與へない。白服の若い看守君も玩具のやうな感じで親しみ易い。治外法權撤廢を叫ばれて居る昨今の支那に斯ふした施設は心強い。　（印畫の複製を嚴禁す）／／●模範監獄（済南）　済南の新式模範監獄は支那としては珍らしい名施設だ。如何にも明るに清々しい此の建物から受ける印象は、牢獄と云ふ陰惨な暗黒さを与へない。白服の若い看守君も玩具のやうな感じで親しみ易い。治外法権撤廃を叫ばれて居る昨今の支那に斯ふした施設は心強い。　（印画の複製を厳禁す）",
    "thumbnail": "http://124.33.215.236/research/atoinga/005/page139/thumbnail.jpg",
    "width": 975
}