{
    "book": "001",
    "height": 760,
    "original": "http://124.33.215.236/research/atoinga/009/page94/x1.jpg",
    "page": 94,
    "text": "●鹽田用鹽汲風車（關東州）　カラ（カラ）とジヤンクのやうな風車の帆が風に煽られると廻轉に連れ鹽田に海水を誘導して汲上げる鹽汲風車の巧妙な裝置はよく自然力を利用して居る。見渡す限り廣々とした鹽田に點々と立つ風車は滿潮時になると一樣に廻轉される。滿洲の製鹽高四十二萬瓩、そのうち州内の生產は二十五萬瓩である。　（印畵の複製を嚴禁す）／／●塩田用塩汲風車（関東州）　カラ（カラ）とジヤンクのやうな風車の帆が風に煽られると廻転に連れ塩田に海水を誘導して汲上げる塩汲風車の巧妙な装置はよく自然力を利用して居る。見渡す限り広々とした塩田に点々と立つ風車は満潮時になると一様に廻転される。満洲の製塩高四十二万瓩、そのうち州内の生産は二十五万瓩である。　（印画の複製を厳禁す）",
    "thumbnail": "http://124.33.215.236/research/atoinga/009/page94/thumbnail.jpg",
    "width": 975
}