{
    "book": "001",
    "height": 750,
    "original": "http://124.33.215.236/research/atoinga/012/page39/x1.jpg",
    "page": 39,
    "text": "●西湖の落暉（杭州）　古來彩管に詩賦に文人墨客に膾炙せられて來た西湖の山水、一度扁舟に棹せば淸澄な湖面に映る四圍の翠巒、岸邊を洗ふ埀柳の葉影に宿る塔影の古雅など眞に蒼翠參差たる景勝で、それ落暉湖面に碎くる一ときは正に筆墨に絕した美觀である。　（印畫の複製を嚴禁す）　／／●西湖の落暉（杭州）　古来彩管に詩賦に文人墨客に膾炙せられて来た西湖の山水、一度扁舟に棹せば清澄な湖面に映る四囲の翠巒、岸辺を洗ふ埀柳《垂柳》の葉影に宿る塔影の古雅など真に蒼翠参差たる景勝で、それ落暉湖面に砕くる一ときは正に筆墨に絶した美観である。　（印画の複製を厳禁す）",
    "thumbnail": "http://124.33.215.236/research/atoinga/012/page39/thumbnail.jpg",
    "width": 900
}