{
    "book": "001",
    "height": 750,
    "original": "http://124.33.215.236/research/atoinga/001/page4/x1.jpg",
    "page": 4,
    "text": "●大連港口（大連）　大連港は延長一萬三千餘尺の防波堤を以て東西北三方を圍み、港内九十四萬坪の海面に三本のピーアが出て居る、その延長一萬二千六百三十尺、一時に十五萬噸の汽船が繫留され、年額約四百五十萬噸の貨物を吞吐する。滿蒙の玄關たるに恥づかしくない。　（印畫の複製を嚴禁す）／／●大連港口（大連）　大連港は延長一万三千余尺の防波堤を以て東西北三方を囲み、港内九十四万坪の海面に三本のピーアが出て居る、その延長一万二千六百三十尺、一時に十五万噸の汽船が繋留され、年額約四百五十万噸の貨物を呑吐する。満蒙の玄関たるに恥づかしくない。　（印画の複製を厳禁す）",
    "thumbnail": "http://124.33.215.236/research/atoinga/001/page4/thumbnail.jpg",
    "width": 985
}