{
    "book": "001",
    "height": 770,
    "original": "http://124.33.215.236/research/atoinga/003/page167/x1.jpg",
    "page": 167,
    "text": "●覇王樹の森（雲南省）　雲南は緯度からすれば亞熱帶地方であるけれども、高原のために氣候は著しく緩和される。併し自然には到るところ熱帶植物の繁茂に依つて珍らしい景觀を呈する。　サボテンの森から小馬を索いてヘヨツコリ現はれた若者の頭にタオルをかけ鳥打帽を阿彌陀に冠つた姿はまさに村の靑年團の模範靑年といふ恰構だ。　（印畫の複製を嚴禁す）／／●覇王樹の森（雲南省）　雲南は緯度からすれば亜熱帯地方であるけれども、高原のために気候は著しく緩和される。併し自然には到るところ熱帯植物の繁茂に依つて珍らしい景観を呈する。　サボテンの森から小馬を索いてヘヨツコリ現はれた若者の頭にタオルをかけ鳥打帽を阿弥陀に冠つた姿はまさに村の青年団の模範青年といふ恰構だ。　（印画の複製を厳禁す）",
    "thumbnail": "http://124.33.215.236/research/atoinga/003/page167/thumbnail.jpg",
    "width": 985
}