{
    "book": "001",
    "height": 765,
    "original": "http://124.33.215.236/research/atoinga/006/page43/x1.jpg",
    "page": 43,
    "text": "●甕聲磖子（延吉地方）　局子街から吉林に通ずる街道上の小市で、もと寒村であつたが、近來鮮農や、支那農民の移住し來るもの日に多く、市も開設され、既に發展して、今では巡警局、兵營、小學校を設け、我が領事館警察の分署もある。約四百の匪賊團が、此地を襲擊せんとして危險に迫つたので、孤立無援の我が分署が本月九日天寶山に引揚を餘儀なくしたといふ物騒な地だ。然し都では見られぬ山地の雪景には、亦捨て難い自然の美しさがある。　（印畫の複製を嚴禁す）／／●甕声磖子（延吉地方）　局子街から吉林に通ずる街道上の小市で、もと寒村であつたが、近来鮮農や、支那農民の移住し来るもの日に多く、市も開設され、既に発展して、今では巡警局、兵営、小学校を設け、我が領事館警察の分署もある。約四百の匪賊団が、此地を襲撃せんとして危険に迫つたので、孤立無援の我が分署が本月九日天宝山に引揚を余儀なくしたといふ物騒な地だ。然し都では見られぬ山地の雪景には、亦捨て難い自然の美しさがある。（印画の複製を厳禁す）",
    "thumbnail": "http://124.33.215.236/research/atoinga/006/page43/thumbnail.jpg",
    "width": 975
}