{
    "book": "001",
    "height": 765,
    "original": "http://124.33.215.236/research/atoinga/006/page6/x1.jpg",
    "page": 6,
    "text": "●林西の城外（東蒙古）　城内には縣公署、公安局、捐税局、監獄、陸軍司令部、兵營などがあり、日本の醫師もゐて施療をやつてゐる。この殷賑な街も、一歩城外に出ると、道の兩側には、罌粟の花が毛氈を敷いたやうに咲き亂れ、豚の群が水溜りに戯れてゐる。左方上部の丘陵地は、蒙將巴布札布が、會て蒙古獨立の反旗を翻したが、事成らず奉軍に包圍され、悲壯な最後を遂げたところだ。　（印畫の複製を嚴禁す）／／●林西の城外（東蒙古）　城内には県公署、公安局、捐税局、監獄、陸軍司令部、兵営などがあり、日本の医師もゐて施療をやつてゐる。この殷賑な街も、一歩城外に出ると、道の両側には、罌粟の花が毛氈を敷いたやうに咲き乱れ、豚の群が水溜りに戯れてゐる。左方上部の丘陵地は、蒙将巴布札布が、会て蒙古独立の反旗を翻したが、事成らず奉軍に包囲され、悲壮な最後を遂げたところだ。　（印画の複製を厳禁す）",
    "thumbnail": "http://124.33.215.236/research/atoinga/006/page6/thumbnail.jpg",
    "width": 975
}