{
    "book": "001",
    "height": 765,
    "original": "http://124.33.215.236/research/atoinga/011/page201/x1.jpg",
    "page": 201,
    "text": "◎三江閘の大東橋　(紹興)　紹興の南仙霞嶺山脈に源を發した浦陽、曹娥の兩江は町の近くを過ぎて杭州灣に注ぎ、一道の運河がその中央を橫斷して東西に貫通し紹興から寧波に通ずる水利の便をなして居る。三江閘はその堰をなすところで滿々たる江上に架せられた石橋が大東橋である。　（印畫の複製を嚴禁す）／／◎三江閘の大東橋　(紹興)　紹興の南仙霞嶺山脈に源を発した浦陽、曹娥の両江は町の近くを過ぎて杭州湾に注ぎ、一道の運河がその中央を横断して東西に貫通し紹興から寧波に通ずる水利の便をなして居る。三江閘はその堰をなすところで満々たる江上に架せられた石橋が大東橋である。　（印画の複製を厳禁す）",
    "thumbnail": "http://124.33.215.236/research/atoinga/011/page201/thumbnail.jpg",
    "width": 930
}