{
    "book": "001",
    "height": 752,
    "original": "http://www.tbcas.jp/ja/lib/lib4/001/page95/x1.jpg",
    "page": 95,
    "text": "支那の上流家庭//支那の上流家庭//雲泥の相異とは支那の富者と貧者との間隔を説明する語ではないかと思はるゝ程それ程物質的生活の差異を上流と下流との家庭に見別けられる、富者必ずしも上流とは言へないが大體に於て上流家庭には富者が多いのは事實である、之等上流家庭の人々は身自ら勞すると云ふ事は殆どなく、家庭は全然自由の樂園其のものゝ如くである、食物は濃厚なものを豐富に攝り、花木小禽を愛づるを以て日を送る、中には一夫多妻の家庭もあつて内面的紛騷も時にあると云ふ。//雲泥の相異とは支那の富者と貧者との間隔を説明する語ではないかと思はるゝ程それ程物質的生活の差異を上流と下流との家庭に見別けられる、富者必ずしも上流とは言へないが大体に於て上流家庭には富者が多いのは事実である、之等上流家庭の人々は身自ら労すると云ふ事は殆どなく、家庭は全然自由の楽園其のものゝ如くである、食物は濃厚なものを豊富に摂り、花木小禽を愛づるを以て日を送る、中には一夫多妻の家庭もあつて内面的紛騒も時にあると云ふ。//",
    "thumbnail": "http://www.tbcas.jp/ja/lib/lib4/001/page95/thumbnail.jpg",
    "width": 957
}