{
    "book": "001",
    "height": 752,
    "original": "http://www.tbcas.jp/ja/lib/lib4/001/page6/x1.jpg",
    "page": 6,
    "text": "警察署 //大連//警察署　（大連）//明治三十八年六月、關東州民政署の編成なりて其一分課として警務部を設け警察行政を行はせ、爾來二十年種々組織に變遷あり民政署より獨立し警務署として警務、保安、衞生等の事務を取扱ふ。大正十四年名稱を大連警察署と改む、大連大廣場中最も古き建築物の一なり。//明治三十八年六月、関東州民政署の編成なりて其一分課として警務部を設け警察行政を行はせ、爾来二十年種々組織に変遷あり民政署より独立し警務署として警務、保安、衛生等の事務を取扱ふ。大正十四年名称を大連警察署と改む、大連大広場中最も古き建築物の一なり。//",
    "thumbnail": "http://www.tbcas.jp/ja/lib/lib4/001/page6/thumbnail.jpg",
    "width": 957
}