{
    "book": "005",
    "height": 722,
    "original": "http://www.tbcas.jp/ja/lib/lib4/005/page94/x1.jpg",
    "page": 94,
    "text": "淸津港//北鮮//清津港　（北鮮）//1928.8//淸津は天成の良港である。波浪荒き朝鮮東海岸には得難き良港として、其の名は久しく世上に喧傳されて來た。從て今突如として吉會線の終端港として、其の名が撰ばれたと報導されても、世人は一向驚かなかつた。｜北に山を負ひ巧に風波を和ぐる天與の地位は、港內の浚渫と相俟つて、將來名實共に北鮮第一港の名を高からしむるであらう。｜（一九二八、八撮影）（印畫の複製を禁ず）//清津は天成の良港である。波浪荒き朝鮮東海岸には得難き良港として、其の名は久しく世上に喧伝されて来た。従て今突如として吉会線の終端港として、其の名が撰ばれたと報導されても、世人は一向驚かなかつた。｜北に山を負ひ巧に風波を和ぐる天与の地位は、港内の浚渫と相俟つて、将来名実共に北鮮第一港の名を高からしむるであらう。｜（一九二八、八撮影）（印画の複製を禁ず）//",
    "thumbnail": "http://www.tbcas.jp/ja/lib/lib4/005/page94/thumbnail.jpg",
    "width": 937
}