{
    "book": "007",
    "height": 727,
    "original": "http://www.tbcas.jp/ja/lib/lib4/007/page38/x1.jpg",
    "page": 38,
    "text": "舞樓を中心に//楚山//舞楼を中心に　（楚山）//1930//楚山は岔溝門の對岸に在る聊の町だ。｜大昔さながらの割木葺きの屋根の不揃がこの町を實質以上に慘めには見せるが、町の中心をなす鍾樓兼舞樓の丸木柱の太さがこの町に數端の貫目を附ける。｜樓の由緒など今は語り次ぐ人も少からう然し、樓前の廣場は、昔乍らの人の盛場だ。（一九三〇年撮影）（印畵の複製を禁ず）//楚山は岔溝門の対岸に在る聊の町だ。｜大昔さながらの割木葺きの屋根の不揃がこの町を実質以上に惨めには見せるが、町の中心をなす鍾楼兼舞楼の丸木柱の太さがこの町に数端の貫目を附ける。｜楼の由緒など今は語り次ぐ人も少からう然し、楼前の広場は、昔乍らの人の盛場だ。（一九三〇年撮影）（印画の複製を禁ず）//",
    "thumbnail": "http://www.tbcas.jp/ja/lib/lib4/007/page38/thumbnail.jpg",
    "width": 937
}