{
    "book": "009",
    "height": 727,
    "original": "http://www.tbcas.jp/ja/lib/lib4/009/page103/x1.jpg",
    "page": 103,
    "text": "玉泉寺//甘肅省蘭州//玉泉寺　（甘粛省蘭州）//黃河を隔て省城と相對して、その河北に聳立する一座の山は、その山頂山腹一群の寺院玉泉寺の名によつて、玉泉山と呼ばれる。｜砂丘のやうに樹一本ない殺風景な山ではあるが、山上の眺望は蓋し絕佳、蘭州盆地の全貌は一眸の下に在り、その盆地を貫流する黃河の雄大な流も亦快哉を叫ばしめる。｜（印畫の複製を禁ず）//黄河を隔て省城と相対して、その河北に聳立する一座の山は、その山頂山腹一群の寺院玉泉寺の名によつて、玉泉山と呼ばれる。｜砂丘のやうに樹一本ない殺風景な山ではあるが、山上の眺望は蓋し絶佳、蘭州盆地の全貌は一眸の下に在り、その盆地を貫流する黄河の雄大な流も亦快哉を叫ばしめる。｜（印画の複製を禁ず）//",
    "thumbnail": "http://www.tbcas.jp/ja/lib/lib4/009/page103/thumbnail.jpg",
    "width": 935
}