{
    "book": "009",
    "height": 727,
    "original": "http://www.tbcas.jp/ja/lib/lib4/009/page71/x1.jpg",
    "page": 71,
    "text": "文王武王陵//陝西省咸陽縣//文王武王陵　（陝西省咸陽県）//咸陽背面の丘陵一帶は、遙に周代に始り、秦漢興亡史を綴る人々の墓に埋つてゐる。周の文王武王の古陵を訪ねて、北門を出ては見たものゝ、附近の百姓に訊いても、誰一人知らない。二十華里餘りをさまやうて、やつと尋ね當てた王陵の哀れさ、淸代重修の跡さへも今は全く潰えて、廟宇の中では、百姓が麥を叩いてゐた。｜（印畫の複製を禁ず）//咸陽背面の丘陵一帯は、遥に周代に始り、秦漢興亡史を綴る人々の墓に埋つてゐる。周の文王武王の古陵を訪ねて、北門を出ては見たものゝ、附近の百姓に訊いても、誰一人知らない。二十華里余りをさまやうて、やつと尋ね当てた王陵の哀れさ、清代重修の跡さへも今は全く潰えて、廟宇の中では、百姓が麦を叩いてゐた。｜（印画の複製を禁ず）//",
    "thumbnail": "http://www.tbcas.jp/ja/lib/lib4/009/page71/thumbnail.jpg",
    "width": 935
}