{
    "book": "013",
    "height": 730,
    "original": "http://www.tbcas.jp/ja/lib/lib4/013/page27/x1.jpg",
    "page": 27,
    "text": "ハロンアルシヤン //蒙古溫泉//ハロンアルシヤン　（蒙古温泉）//浴客の少ない關係上冬の溫泉は澄みきつて鏡の樣に透明だ、小さな魚が肌の周圍をチヨロ(チヨロ)泳ぎ週つて可愛らしい。蒙古人の小供達が無邪氣な心特に靈泉を蒙古人特有の碗に吸みながら微笑むのも靈泉の占景としてふさはしい。(印畫の複製を禁ず)//浴客の少ない関係上冬の温泉は澄みきつて鏡の様に透明だ、小さな魚が肌の周囲をチヨロ(チヨロ)泳ぎ週つて可愛らしい。蒙古人の小供達が無邪気な心特に霊泉を蒙古人特有の碗に吸みながら微笑むのも霊泉の占景としてふさはしい。(印画の複製を禁ず)//",
    "thumbnail": "http://www.tbcas.jp/ja/lib/lib4/013/page27/thumbnail.jpg",
    "width": 917
}