{
    "book": "014",
    "height": 722,
    "original": "http://www.tbcas.jp/ja/lib/lib4/014/page107/x1.jpg",
    "page": 107,
    "text": "閩江の筏//福建省//閩江の筏　（福建省）//福建省は山嶽の重疊たる關係上松、杉等の木材の產地として知られてゐる中でも杉は其の主材で、閩江の上流、延平、建寧、その他の上流に產し此等地方から江を流して來る筏も福州に到着すれば解體せられ、海外に輸出されてゐる今や筏は福州間近くなつたので繫筏準備にいそしんでゐる。｜（印畫の複製を禁ず）//福建省は山岳の重畳たる関係上松、杉等の木材の産地として知られてゐる中でも杉は其の主材で、閩江の上流、延平、建寧、その他の上流に産し此等地方から江を流して来る筏も福州に到着すれば解体せられ、海外に輸出されてゐる今や筏は福州間近くなつたので繋筏準備にいそしんでゐる。｜（印画の複製を禁ず）//",
    "thumbnail": "http://www.tbcas.jp/ja/lib/lib4/014/page107/thumbnail.jpg",
    "width": 905
}